bootstrap_CIHT/__init__.py
bootstrap_CIHT/bootstrap_CIHT.py
bootstrap_CIHT-0.1.1.dist-info/METADATA
bootstrap_CIHT-0.1.1.dist-info/WHEEL
bootstrap_CIHT-0.1.1.dist-info/top_level.txt
bootstrap_CIHT-0.1.1.dist-info/RECORD
