Metadata-Version: 2.1
Name: bootstrap-CIHT
Version: 0.1.1
Summary: Confidence intervals & hypothesis testing using bootstrap samples
Home-page: https://github.com/ensst6/bootstrap_CIHT
Author: Erik Sorensen
Author-email: ens59327@gmail.com
License: UNKNOWN
Project-URL: Bug Tracker, https://github.com/ensst6/bootstrap_CIHT/issues
Platform: UNKNOWN
Classifier: Programming Language :: Python :: 3
Classifier: License :: OSI Approved :: MIT License
Classifier: Operating System :: OS Independent
Requires-Python: >=3.6
Requires-Dist: numpy
Requires-Dist: pandas
Requires-Dist: matplotlib
